LICENSE.rst
MANIFEST.in
README.rst
requirements.txt
setup.cfg
setup.py
mastcasjobs/__init__-orig.py
mastcasjobs/__init__.py
mastcasjobs.egg-info/PKG-INFO
mastcasjobs.egg-info/SOURCES.txt
mastcasjobs.egg-info/dependency_links.txt
mastcasjobs.egg-info/not-zip-safe
mastcasjobs.egg-info/requires.txt
mastcasjobs.egg-info/top_level.txt