Metadata-Version: 2.1
Name: mastcasjobs
Version: 0.0.8
Summary: An interface to MAST CasJobs.
Home-page: https://github.com/rlwastro/mastcasjobs
Author: Richard L. White
Author-email: rlw@stsci.edu
License: MIT
Platform: OS Independent
Classifier: Development Status :: 3 - Alpha
Classifier: Intended Audience :: Developers
Classifier: Intended Audience :: Science/Research
Classifier: License :: OSI Approved :: MIT License
Classifier: Operating System :: OS Independent
Classifier: Programming Language :: Python
Requires-Python: >=3.5
License-File: LICENSE.rst
Requires-Dist: requests
Requires-Dist: casjobs>=0.0.2
Requires-Dist: astropy
